tuxsay/main.py
tuxsay-0.1.4.dist-info/entry_points.txt
tuxsay-0.1.4.dist-info/WHEEL
tuxsay-0.1.4.dist-info/METADATA
tuxsay-0.1.4.dist-info/RECORD
