Metadata-Version: 2.1
Name: tuxsay
Version: 0.1.4
Summary: A CLI like cowsay but its Tux as your host
License: MIT
Author: Arghya Sarkar
Author-email: arghyasarkar.nolan@gmail.com
Requires-Python: >=3.6,<4.0
Classifier: License :: OSI Approved :: MIT License
Classifier: Programming Language :: Python :: 3
Classifier: Programming Language :: Python :: 3.6
Classifier: Programming Language :: Python :: 3.7
Classifier: Programming Language :: Python :: 3.8
Classifier: Programming Language :: Python :: 3.9
Requires-Dist: click (>=8.0.1,<9.0.0)
Requires-Dist: click-help-colors (>=0.9.1,<0.10.0)
Requires-Dist: clipboard (>=0.0.4,<0.0.5)
